<annotation>
	<folder>images</folder>
	<filename>img90.jpg</filename>
	<path>C:\python_notebooks\Machine_learning_Engineer_Nanodegree\projects\capstone_object_detection_new\images\img90.jpg</path>
	<source>
		<database>Unknown</database>
	</source>
	<size>
		<width>900</width>
		<height>900</height>
		<depth>3</depth>
	</size>
	<segmented>0</segmented>
	<object>
		<name>Mickey</name>
		<pose>Unspecified</pose>
		<truncated>0</truncated>
		<difficult>0</difficult>
		<bndbox>
			<xmin>29</xmin>
			<ymin>28</ymin>
			<xmax>500</xmax>
			<ymax>533</ymax>
		</bndbox>
	</object>
	<object>
		<name>Mickey</name>
		<pose>Unspecified</pose>
		<truncated>0</truncated>
		<difficult>0</difficult>
		<bndbox>
			<xmin>661</xmin>
			<ymin>447</ymin>
			<xmax>873</xmax>
			<ymax>645</ymax>
		</bndbox>
	</object>
</annotation>
